clovars/IO/__init__.py
clovars/IO/colony_loader.py
clovars/IO/parameter_validator.py
clovars/IO/simulation_loader.py
clovars/IO/simulation_writer.py
clovars/IO/well_loader.py
clovars/__init__.py
clovars/abstract/__init__.py
clovars/abstract/cell_node.py
clovars/abstract/circle.py
clovars/bio/__init__.py
clovars/bio/cell.py
clovars/bio/colony.py
clovars/bio/treatment.py
clovars/bio/well.py
clovars/default_settings/data.csv
clovars/default_settings/default_analysis.toml
clovars/default_settings/default_colonies.toml
clovars/default_settings/default_fit.toml
clovars/default_settings/default_run.toml
clovars/default_settings/default_view.toml
clovars/gui/__init__.py
clovars/gui/clovars_main_window.py
clovars/gui/params_manager.py
clovars/main.py
clovars/scientific/__init__.py
clovars/scientific/brownian_motion.py
clovars/scientific/cell_signal.py
clovars/scientific/curve_estimator.py
clovars/scientific/curves.py
clovars/scientific/sctypes.py
clovars/simulation/__init__.py
clovars/simulation/analysis/__init__.py
clovars/simulation/analysis/analyse_simulation.py
clovars/simulation/analysis/simulation_analyzer.py
clovars/simulation/fit/__init__.py
clovars/simulation/fit/data_fitter.py
clovars/simulation/fit/fit_experimental_data.py
clovars/simulation/run/__init__.py
clovars/simulation/run/run_simulation.py
clovars/simulation/run/simulation_runner.py
clovars/simulation/view/__init__.py
clovars/simulation/view/simulation_viewer.py
clovars/simulation/view/treatment_drawer.py
clovars/simulation/view/tree_drawer_2D.py
clovars/simulation/view/tree_drawer_3D.py
clovars/simulation/view/view_simulation.py
clovars/utils/__init__.py
clovars/utils/exceptions.py
clovars/utils/mixins/__init__.py
clovars/utils/mixins/path_creator.py
clovars/utils/mixins/quiet_printer.py
clovars-0.2.3.dist-info/entry_points.txt
clovars-0.2.3.dist-info/LICENSE.md
clovars-0.2.3.dist-info/WHEEL
clovars-0.2.3.dist-info/METADATA
clovars-0.2.3.dist-info/RECORD
