Metadata-Version: 2.1
Name: clovars
Version: 0.2.3
Summary: Clonal Variability Simulation
Home-page: http://www.ufrgs.br/labsinal/clovars/
License: MIT
Keywords: Simulation,Biology,Single Cells,Heterogeneity,Fitness
Author: Juliano Faccioni
Author-email: julianofaccioni@gmail.com
Requires-Python: >=3.8,<4.0
Classifier: License :: OSI Approved :: MIT License
Classifier: Programming Language :: Python :: 3
Classifier: Programming Language :: Python :: 3.10
Classifier: Programming Language :: Python :: 3.8
Classifier: Programming Language :: Python :: 3.9
Requires-Dist: ete3 (>=3.1.2,<4.0.0)
Requires-Dist: matplotlib (>=3.5.1,<4.0.0)
Requires-Dist: numpy (>=1.22.2,<2.0.0)
Requires-Dist: pandas (>=1.4.1,<2.0.0)
Requires-Dist: scipy (>=1.8.0,<2.0.0)
Requires-Dist: seaborn (>=0.11.2,<0.12.0)
Requires-Dist: toml (>=0.10.2,<0.11.0)
Project-URL: Documentation, http://www.ufrgs.br/labsinal/clovars/docs
Project-URL: Repository, https://github.com/jfaccioni/clovars
